stupid_python_package/__init__.py
stupid_python_package-0.0.3.dist-info/WHEEL
stupid_python_package-0.0.3.dist-info/METADATA
stupid_python_package-0.0.3.dist-info/RECORD
